{
  "products": [
    {
      "id": 1,
      "title": "San pham A",
      "description": "Mo ta san pham a",
      "price": 111,
      "image": "https://encrypted-tbn0.gstatic.com/images?q=tbn:ANd9GcQ2RWQ0h1LZxZHLad9eB0JVgBlzqEPPrZVeQQ&s"
    },
    {
      "id": 2,
      "title": "San pham B",
      "description": "Mo ta san pham a",
      "price": 111,
      "image": "https://encrypted-tbn0.gstatic.com/images?q=tbn:ANd9GcQ2RWQ0h1LZxZHLad9eB0JVgBlzqEPPrZVeQQ&s"
    },
    {
      "id": 3,
      "title": "San pham C",
      "description": "Mo ta san pham a",
      "price": 111,
      "image": "https://encrypted-tbn0.gstatic.com/images?q=tbn:ANd9GcQ2RWQ0h1LZxZHLad9eB0JVgBlzqEPPrZVeQQ&s"
    },
    {
      "id": 4,
      "title": "San pham C",
      "description": "Mo ta san pham a",
      "price": 111,
      "image": "https://encrypted-tbn0.gstatic.com/images?q=tbn:ANd9GcQ2RWQ0h1LZxZHLad9eB0JVgBlzqEPPrZVeQQ&s"
    }
  ],
  "users": [
    {
      "email": "sdfs@gmail.com",
      "password": "$2a$10$bkz44AK98cRiMqSc3qr3t.tHgLUC1jLAH3PQFK5sjQycyjIw8pT76",
      "id": 1
    }
  ]
}